prepaidcsValueFetcher.py
prepaidcsValueFetcher-0.0.3.dist-info/LICENSE
prepaidcsValueFetcher-0.0.3.dist-info/METADATA
prepaidcsValueFetcher-0.0.3.dist-info/WHEEL
prepaidcsValueFetcher-0.0.3.dist-info/top_level.txt
prepaidcsValueFetcher-0.0.3.dist-info/RECORD
